COPYING
MANIFEST.in
NEWS.rst
README.rst
setup.py
byoc/__init__.py
byoc/errors.py
byoc/options.py
byoc/parsers.py
byoc/registries.py
byoc/stacks.py
byoc/stores.py
byoc/tests/__init__.py
byoc/tests/test_options.py
byoc/tests/test_parsers.py
byoc/tests/test_registries.py
byoc/tests/test_stacks.py
byoc/tests/test_stores.py
byoc/tests/test_styles.py
python3_byoc.egg-info/PKG-INFO
python3_byoc.egg-info/SOURCES.txt
python3_byoc.egg-info/dependency_links.txt
python3_byoc.egg-info/top_level.txt