Metadata-Version: 2.1
Name: python3-byoc
Version: 3.0.1
Summary: Build Your Own Config framework.
Home-page: https://launchpad.net/byoc
Author: Vincent Ladeuil
Author-email: v.ladeuil+lp@free.fr
License: GPLv3
License-File: COPYING
